ultracube/__init__.py
ultracube-0.0.1.dist-info/LICENSE
ultracube-0.0.1.dist-info/METADATA
ultracube-0.0.1.dist-info/WHEEL
ultracube-0.0.1.dist-info/top_level.txt
ultracube-0.0.1.dist-info/zip-safe
ultracube-0.0.1.dist-info/RECORD
